gfe_fhir-0.0.1.dist-info/METADATA
gfe_fhir-0.0.1.dist-info/RECORD
gfe_fhir-0.0.1.dist-info/WHEEL
gfe_fhir-0.0.1.dist-info/top_level.txt
gfefhir/__init__.py
gfefhir/gfefhir.py
