Metadata-Version: 2.1
Name: gfe-fhir
Version: 0.0.1
Summary: Python Boilerplate contains all the boilerplate you need to create a Python package.
Home-page: https://github.com/mhalagan-nmdp/gfefhir
Author: Michael Halagan
Author-email: mhalagan@nmdp.org
License: LGPL 3.0
Keywords: gfefhir
Platform: UNKNOWN
Classifier: Development Status :: 2 - Pre-Alpha
Classifier: Intended Audience :: Developers
Classifier: License :: OSI Approved :: GNU Lesser General Public License v3 (LGPLv3)
Classifier: Natural Language :: English
Classifier: Programming Language :: Python :: 2
Classifier: Programming Language :: Python :: 2.6
Classifier: Programming Language :: Python :: 2.7
Classifier: Programming Language :: Python :: 3
Classifier: Programming Language :: Python :: 3.3
Classifier: Programming Language :: Python :: 3.4
Classifier: Programming Language :: Python :: 3.5
Requires-Dist: biopython (==1.72)
Requires-Dist: certifi (==2018.4.16)
Requires-Dist: chardet (==3.0.4)
Requires-Dist: fhirclient (==3.2.0)
Requires-Dist: gfe-client (==0.0.2)
Requires-Dist: idna (==2.7)
Requires-Dist: isodate (==0.6.0)
Requires-Dist: numpy (==1.15.0)
Requires-Dist: python-dateutil (==2.7.3)
Requires-Dist: requests (==2.19.1)
Requires-Dist: six (==1.11.0)
Requires-Dist: urllib3 (==1.23)
